frigidaire/__init__.py
frigidaire/rate_limit.py
frigidaire/rl_autowrap.py
frigidaire/signature_generator.py
frigidaire-0.18.28.dist-info/licenses/LICENSE
frigidaire-0.18.28.dist-info/METADATA
frigidaire-0.18.28.dist-info/WHEEL
frigidaire-0.18.28.dist-info/top_level.txt
frigidaire-0.18.28.dist-info/RECORD
