Metadata-Version: 2.4
Name: frigidaire
Version: 0.18.28
Summary: Python API for the Frigidaire 2.0 App
Home-page: https://github.com/bm1549/frigidaire
Author: Brian Marks
License: MIT
Classifier: Programming Language :: Python :: 3
Classifier: License :: OSI Approved :: MIT License
Classifier: Operating System :: OS Independent
License-File: LICENSE
Requires-Dist: certifi>=2020.12.5
Requires-Dist: chardet>=4.0.0
Requires-Dist: idna>=2.10
Requires-Dist: requests>=2.25.1
Requires-Dist: urllib3>=1.26.4
Dynamic: author
Dynamic: classifier
Dynamic: description
Dynamic: description-content-type
Dynamic: home-page
Dynamic: license
Dynamic: license-file
Dynamic: requires-dist
Dynamic: summary
